funfake/__init__.py
funfake/base.py
funfake/headers/__init__.py
funfake/headers/browsers.py
funfake/headers/core.py
funfake/headers/headers.py
funfake/headers/platforms.py
funfake/names/__init__.py
funfake/names/core.py
funfake/names/scenarios.py
funfake/phones/__init__.py
funfake/phones/core.py
funfake-1.1.5.dist-info/METADATA
funfake-1.1.5.dist-info/WHEEL
funfake-1.1.5.dist-info/top_level.txt
funfake-1.1.5.dist-info/RECORD
