Metadata-Version: 2.4
Name: funfake
Version: 1.1.5
Summary: A lightweight Python library for generating realistic HTTP headers to simulate various browsers and operating systems
Author-email: 牛哥 <niuliangtao@qq.com>, farfarfun <farfarfun@qq.com>
Maintainer-email: 牛哥 <niuliangtao@qq.com>, farfarfun <farfarfun@qq.com>
Project-URL: Organization, https://github.com/farfarfun
Project-URL: Repository, https://github.com/farfarfun/funfake
Project-URL: Releases, https://github.com/farfarfun/funfake/releases
Requires-Python: >=3.8
